datalad_getexec/__init__.py
datalad_getexec/_version.py
datalad_getexec/compat.py
datalad_getexec/getexec.py
datalad_getexec/remote.py
datalad_getexec/spec.py
datalad_getexec-0.1.0.dist-info/LICENSE
datalad_getexec-0.1.0.dist-info/METADATA
datalad_getexec-0.1.0.dist-info/WHEEL
datalad_getexec-0.1.0.dist-info/entry_points.txt
datalad_getexec-0.1.0.dist-info/top_level.txt
datalad_getexec-0.1.0.dist-info/RECORD
