Metadata-Version: 2.1
Name: datalad-getexec
Version: 0.1.0
Summary: DataLad extension for code execution in get commands
Home-page: https://github.com/matrss/datalad-getexec
Author: Matthias Riße
Author-email: m.risse@fz-juelich.de
License: MIT
Classifier: Programming Language :: Python
Classifier: License :: OSI Approved :: MIT License
Classifier: Programming Language :: Python :: 3
Requires-Python: >=3.8
License-File: LICENSE
Requires-Dist: datalad (>=0.17.0)
Requires-Dist: annexremote (>=1.6.0)
Provides-Extra: devel
Requires-Dist: pytest ; extra == 'devel'
Requires-Dist: coverage ; extra == 'devel'
